azure/mgmt/advisor/__init__.py
azure/mgmt/advisor/_advisor_management_client.py
azure/mgmt/advisor/_configuration.py
azure/mgmt/advisor/version.py
azure/mgmt/advisor/models/__init__.py
azure/mgmt/advisor/models/_advisor_management_client_enums.py
azure/mgmt/advisor/models/_models.py
azure/mgmt/advisor/models/_models_py3.py
azure/mgmt/advisor/models/_paged_models.py
azure/mgmt/advisor/operations/__init__.py
azure/mgmt/advisor/operations/_configurations_operations.py
azure/mgmt/advisor/operations/_operations.py
azure/mgmt/advisor/operations/_recommendation_metadata_operations.py
azure/mgmt/advisor/operations/_recommendations_operations.py
azure/mgmt/advisor/operations/_suppressions_operations.py
azure_mgmt_advisor-4.0.0.dist-info/METADATA
azure_mgmt_advisor-4.0.0.dist-info/WHEEL
azure_mgmt_advisor-4.0.0.dist-info/top_level.txt
azure_mgmt_advisor-4.0.0.dist-info/RECORD
